chainladder/__init__.py
chainladder/adjustments/__init__.py
chainladder/adjustments/berqsherm.py
chainladder/adjustments/bootstrap.py
chainladder/adjustments/parallelogram.py
chainladder/adjustments/trend.py
chainladder/adjustments/tests/__init__.py
chainladder/adjustments/tests/test_berqsherm.py
chainladder/adjustments/tests/test_bootstrap.py
chainladder/adjustments/tests/test_parallelogram.py
chainladder/adjustments/tests/test_trend.py
chainladder/core/__init__.py
chainladder/core/base.py
chainladder/core/common.py
chainladder/core/correlation.py
chainladder/core/display.py
chainladder/core/dunders.py
chainladder/core/io.py
chainladder/core/pandas.py
chainladder/core/slice.py
chainladder/core/triangle.py
chainladder/core/tests/__init__.py
chainladder/core/tests/rtest_correlation.py
chainladder/core/tests/test_arithmetic.py
chainladder/core/tests/test_correlation.py
chainladder/core/tests/test_display.py
chainladder/core/tests/test_grain.py
chainladder/core/tests/test_slicing.py
chainladder/core/tests/test_triangle.py
chainladder/development/__init__.py
chainladder/development/barnzehn.py
chainladder/development/base.py
chainladder/development/clark.py
chainladder/development/constant.py
chainladder/development/development.py
chainladder/development/glm.py
chainladder/development/incremental.py
chainladder/development/learning.py
chainladder/development/munich.py
chainladder/development/outstanding.py
chainladder/development/tests/__init__.py
chainladder/development/tests/rtest_clark.py
chainladder/development/tests/rtest_development.py
chainladder/development/tests/rtest_munich.py
chainladder/development/tests/test_barnzehn.py
chainladder/development/tests/test_constant.py
chainladder/development/tests/test_development.py
chainladder/development/tests/test_glm.py
chainladder/development/tests/test_incremental.py
chainladder/development/tests/test_learning.py
chainladder/development/tests/test_munich.py
chainladder/development/tests/test_outstanding.py
chainladder-0.9.1.dist-info/licenses/LICENSE
chainladder-0.9.1.dist-info/METADATA
chainladder-0.9.1.dist-info/WHEEL
chainladder-0.9.1.dist-info/top_level.txt
chainladder-0.9.1.dist-info/RECORD
