Metadata-Version: 2.4
Name: chainladder
Version: 0.9.1
Summary: Chainladder Package - P&C Loss Reserving package
Author-email: John Bogaardt <jbogaardt@gmail.com>
Maintainer-email: John Bogaardt <jbogaardt@gmail.com>
License: MPL-2.0
Project-URL: Homepage, https://github.com/casact/chainladder-python
Project-URL: Documentation, https://chainladder-python.readthedocs.io/
Project-URL: Repository, https://github.com/casact/chainladder-python
Project-URL: Bug Tracker, https://github.com/casact/chainladder-python/issues
Keywords: actuarial,reserving,insurance,chainladder,IBNR
Classifier: Development Status :: 4 - Beta
Classifier: Intended Audience :: Developers
Classifier: Intended Audience :: Science/Research
Classifier: License :: OSI Approved :: Mozilla Public License 2.0 (MPL 2.0)
Classifier: Operating System :: OS Independent
Classifier: Programming Language :: Python :: 3
Classifier: Programming Language :: Python :: 3.9
Classifier: Programming Language :: Python :: 3.10
Classifier: Programming Language :: Python :: 3.11
Classifier: Programming Language :: Python :: 3.12
Classifier: Programming Language :: Python :: 3.13
Classifier: Programming Language :: Python :: 3.14
Requires-Python: >=3.9
License-File: LICENSE
Requires-Dist: pandas<3.0,>=2.0
Requires-Dist: scikit-learn>1.4.2
Requires-Dist: numba>0.54
Requires-Dist: sparse>=0.9
Requires-Dist: matplotlib
Requires-Dist: dill
Requires-Dist: patsy
Provides-Extra: dev
Requires-Dist: lxml; extra == "dev"
Requires-Dist: pytest; extra == "dev"
Requires-Dist: pytest-cov; extra == "dev"
Requires-Dist: pytest-xdist; extra == "dev"
Requires-Dist: jinja2; extra == "dev"
Requires-Dist: ipython; extra == "dev"
Requires-Dist: ipykernel; extra == "dev"
Provides-Extra: docs
Requires-Dist: sphinx; extra == "docs"
Requires-Dist: sphinx-rtd-theme; extra == "docs"
Requires-Dist: nbsphinx; extra == "docs"
Requires-Dist: numpydoc; extra == "docs"
Requires-Dist: jupyter-book<2.0; extra == "docs"
Requires-Dist: sphinx-togglebutton; extra == "docs"
Requires-Dist: ipython; extra == "docs"
Requires-Dist: parso>=0.8; extra == "docs"
Requires-Dist: polars; extra == "docs"
Requires-Dist: statsmodels; extra == "docs"
Provides-Extra: test
Requires-Dist: lxml; extra == "test"
Requires-Dist: nbmake; extra == "test"
Requires-Dist: pytest; extra == "test"
Requires-Dist: jinja2; extra == "test"
Requires-Dist: ipython; extra == "test"
Requires-Dist: pytest-cov; extra == "test"
Requires-Dist: dask; extra == "test"
Requires-Dist: statsmodels; extra == "test"
Provides-Extra: performance
Requires-Dist: dask; extra == "performance"
Requires-Dist: cupy; extra == "performance"
Provides-Extra: all
Requires-Dist: chainladder[dev,docs,test]; extra == "all"
Dynamic: license-file
